Metadata-Version: 2.1
Name: varuploader
Version: 0.0.2
Summary: Variscite Recovery SD Card Uploader Tool
Home-page: https://github.com/dorta/var-uploader
Author: Alifer Moraes, Diego Dorta
License: BSD-3-Clause
Platform: UNKNOWN
Classifier: Development Status :: 3 - Alpha
Classifier: Intended Audience :: Information Technology
Classifier: Natural Language :: English
Classifier: Operating System :: Other OS
Classifier: Programming Language :: Python :: 3.7
